selenium_stealth/__init__.py
selenium_stealth/chrome_app.py
selenium_stealth/chrome_runtime.py
selenium_stealth/hairline_fix.py
selenium_stealth/iframe_content_window.py
selenium_stealth/media_codecs.py
selenium_stealth/navigator_languages.py
selenium_stealth/navigator_permissions.py
selenium_stealth/navigator_plugins.py
selenium_stealth/navigator_vendor.py
selenium_stealth/navigator_webdriver.py
selenium_stealth/user_agent_override.py
selenium_stealth/utils.py
selenium_stealth/webgl_vendor.py
selenium_stealth/window_outerdimensions.py
selenium_stealth/wrapper.py
selenium_stealth/js/chrome.app.js
selenium_stealth/js/chrome.csi.js
selenium_stealth/js/chrome.loadTimes.js
selenium_stealth/js/chrome.runtime.js
selenium_stealth/js/hairline.fix.js
selenium_stealth/js/iframe.contentWindow.js
selenium_stealth/js/media.codecs.js
selenium_stealth/js/navigator.languages.js
selenium_stealth/js/navigator.permissions.js
selenium_stealth/js/navigator.plugins.js
selenium_stealth/js/navigator.vendor.js
selenium_stealth/js/navigator.webdriver.js
selenium_stealth/js/utils.js
selenium_stealth/js/webgl.vendor.js
selenium_stealth/js/window.outerdimensions.js
selenium_stealth-1.0.5.dist-info/LICENSE.txt
selenium_stealth-1.0.5.dist-info/METADATA
selenium_stealth-1.0.5.dist-info/WHEEL
selenium_stealth-1.0.5.dist-info/top_level.txt
selenium_stealth-1.0.5.dist-info/RECORD
