Metadata-Version: 2.1
Name: selenium-stealth
Version: 1.0.5
Summary: Trying to make python selenium more stealthy.
Home-page: https://github.com/diprajpatra/selenium-stealth
Author: Dipraj Patra
Author-email: diprajpatra@gmail.com
License: UNKNOWN
Platform: UNKNOWN
Classifier: License :: OSI Approved :: MIT License
Classifier: Operating System :: OS Independent
Requires-Python: >=3
